mcp_audit/__init__.py
mcp_audit-0.9.2.dist-info/METADATA
mcp_audit-0.9.2.dist-info/WHEEL
mcp_audit-0.9.2.dist-info/entry_points.txt
mcp_audit-0.9.2.dist-info/top_level.txt
mcp_audit-0.9.2.dist-info/RECORD
