Metadata-Version: 2.4
Name: mcp-audit
Version: 0.9.2
Summary: DEPRECATED: This package has been renamed to token-audit.
License-Expression: MIT
Requires-Python: >=3.10
Requires-Dist: token-audit>=1.0.0
